lvis/__init__.py
lvis/colormap.py
lvis/eval.py
lvis/lvis.py
lvis/results.py
lvis/vis.py
mmlvis-10.5.3.dist-info/METADATA
mmlvis-10.5.3.dist-info/WHEEL
mmlvis-10.5.3.dist-info/top_level.txt
mmlvis-10.5.3.dist-info/RECORD
